{"cameraMode":{"drawMode":0,"name":"Shaded","section":"Shading Mode"},"sceneLighting":true,"audioPlay":false,"sceneViewState":{"m_AlwaysRefresh":false,"showFog":true,"showSkybox":true,"showFlares":true,"showImageEffects":true,"showParticleSystems":true,"showVisualEffectGraphs":true,"m_FxEnabled":true},"in2DMode":false,"pivot":{"x":3.327918529510498,"y":1.8339204788208008,"z":1.2647628784179688},"rotation":{"x":0.3333841562271118,"y":0.0056566898711025719,"z":-0.002000323962420225,"w":0.9427695870399475},"size":5.81698751449585,"orthographic":false}